O_money/__init__.py
O_money/models.py
O_money/o_webpay.py
O_money-0.0.10.dist-info/LICENSE.txt
O_money-0.0.10.dist-info/METADATA
O_money-0.0.10.dist-info/WHEEL
O_money-0.0.10.dist-info/entry_points.txt
O_money-0.0.10.dist-info/top_level.txt
O_money-0.0.10.dist-info/RECORD
